<?xml version='1.0' encoding='UTF-8'?>
<sect1 id="ch0006s0010" role="Heading">
         <title>Exit, Voice, Loyalty, and Neglect</title>
         <para role="Para">The Exit, Voice, Loyalty, and Neglect (EVLN) Model (Hirshman, <emphasis role="CitationRef">
               <link linkend="ch0006s0012bib01">1970</link>
            </emphasis>) examines how intent to leave an organization or stay is based upon the organizational culture and how employees take cues from the culture in determining their decisions. Employees who encounter difficult situations (e.g., bullying) within the workplace and desire a change in position may make the decision to either transfer to a different department or resign and <emphasis role="bold">exit</emphasis> the organization. Some employees may choose to <emphasis role="bold">voice</emphasis> their concerns to the organization about dissatisfying situations in the workplace like bullying, while others decide that silence is the only option to survive and remain in their current position. Employees’ <emphasis role="bold">loyalty</emphasis> to their organizations ultimately will drive their decision to resign or remain in workplace situations that may be unhealthy. Lastly, the <emphasis role="bold">neglecting</emphasis> of workplace incidences that are uncivil and result in the continuation of bullying may temporarily lead to employee retention. However, it is the ongoing interface with dysfunctional work environments that will impact productivity and profitability and lead to the decision of employees to decide that in order to maintain physical and mental health, that resignation is their best option.</para>
      </sect1>
      
